setup.py
cc_xjhdemo01.egg-info/PKG-INFO
cc_xjhdemo01.egg-info/SOURCES.txt
cc_xjhdemo01.egg-info/dependency_links.txt
cc_xjhdemo01.egg-info/requires.txt
cc_xjhdemo01.egg-info/top_level.txt
xjhpipdemo01/__init__.py
xjhpipdemo01/cc.model.py
xjhpipdemo01/cc.utils.py